{
  "//": "THIS FILE IS AUTOGENERATED. DO NOT MANIPULATE OR COMMIT",
  "templates": {
    "blank": [],
    "hello-world": [],
    "hello-voice": [
      {
        "key": "TWILIO_VOICE_WEBHOOK_URL",
        "required": true,
        "format": "text",
        "description": "The path to the webhook",
        "link": null,
        "default": "/hello-voice",
        "configurable": false,
        "contentKey": null
      }
    ],
    "hello-messaging": [
      {
        "key": "TWILIO_SMS_WEBHOOK_URL",
        "required": true,
        "format": "text",
        "description": "The path to the webhook",
        "link": null,
        "default": "/hello-messaging",
        "configurable": false,
        "contentKey": null
      }
    ],
    "never-gonna-give-you-up": [
      {
        "key": "TWILIO_VOICE_WEBHOOK_URL",
        "required": true,
        "format": "text",
        "description": "The path to the webhook",
        "link": null,
        "default": "/never-gonna-give-you-up",
        "configurable": false,
        "contentKey": null
      }
    ],
    "forward-call": [
      {
        "key": "MY_PHONE_NUMBER",
        "required": true,
        "format": "phone_number",
        "description": "Calls made to your Twilio number will get forwarded to this e164-formatted phone number",
        "link": "https://www.twilio.com/docs/glossary/what-e164",
        "default": "+12223334444",
        "configurable": true,
        "contentKey": null
      },
      {
        "key": "TWILIO_VOICE_WEBHOOK_URL",
        "required": true,
        "format": "text",
        "description": "The path to the webhook",
        "link": null,
        "default": "/forward-call",
        "configurable": false,
        "contentKey": null
      }
    ],
    "forward-message": [
      {
        "key": "MY_PHONE_NUMBER",
        "required": true,
        "format": "phone_number",
        "description": "Messages sent to your Twilio number will get forwarded to this E.164-formatted phone number",
        "link": "https://www.twilio.com/docs/glossary/what-e164",
        "default": "+12223334444",
        "configurable": true,
        "contentKey": null
      },
      {
        "key": "TWILIO_SMS_WEBHOOK_URL",
        "required": true,
        "format": "text",
        "description": "The path to the webhook",
        "link": null,
        "default": "/forward-message",
        "configurable": false,
        "contentKey": null
      }
    ],
    "forward-message-multiple": [
      {
        "key": "FORWARDING_NUMBERS",
        "required": true,
        "format": "list(phone_number)",
        "description": "A list of numbers in E.164 format you want to forward incoming messages to, separated by commas",
        "link": null,
        "default": "+12223334444,+491761234567",
        "configurable": true,
        "contentKey": null
      },
      {
        "key": "TWILIO_SMS_WEBHOOK_URL",
        "required": true,
        "format": "text",
        "description": "The path to the webhook",
        "link": null,
        "default": "/forward-message-multiple",
        "configurable": false,
        "contentKey": null
      }
    ],
    "forward-message-sendgrid": [
      {
        "key": "SENDGRID_API_KEY",
        "required": true,
        "format": "secret",
        "description": "Your SendGrid API key",
        "link": "https://sendgrid.com/docs/ui/account-and-settings/api-keys/",
        "default": null,
        "configurable": true,
        "contentKey": null
      },
      {
        "key": "TO_EMAIL_ADDRESS",
        "required": true,
        "format": "email",
        "description": "Messages sent to your Twilio number will be forwarded to this email address",
        "link": null,
        "default": null,
        "configurable": true,
        "contentKey": null
      },
      {
        "key": "FROM_EMAIL_ADDRESS",
        "required": true,
        "format": "email",
        "description": "The email address that SendGrid should send the email from",
        "link": null,
        "default": null,
        "configurable": true,
        "contentKey": null
      },
      {
        "key": "TWILIO_SMS_WEBHOOK_URL",
        "required": true,
        "format": "text",
        "description": "The path to the webhook",
        "link": null,
        "default": "/forward-message-sendgrid",
        "configurable": false,
        "contentKey": null
      }
    ],
    "voicemail": [
      {
        "key": "MY_PHONE_NUMBER",
        "required": true,
        "format": "phone_number",
        "description": "Calls made to your Twilio number will get forwarded to this E.164-formatted phone number",
        "link": "https://www.twilio.com/docs/glossary/what-e164",
        "default": "+12223334444",
        "configurable": true,
        "contentKey": null
      },
      {
        "key": "TIMEZONE_OFFSET",
        "required": false,
        "format": "integer",
        "description": "The timezone offset from UTC to check for business hours (-8 for PST, -5 for EST)",
        "link": null,
        "default": "0",
        "configurable": true,
        "contentKey": null
      },
      {
        "key": "WORK_WEEK_START",
        "required": false,
        "format": "integer",
        "description": "Day of the week where the business hours should start applying. 0-6 = Sunday - Saturday. Default is set to 1, which is Monday",
        "link": null,
        "default": "1",
        "configurable": true,
        "contentKey": null
      },
      {
        "key": "WORK_WEEK_END",
        "required": false,
        "format": "integer",
        "description": "Day of the week after which the business hours should stop applying. 0-6 = Sunday - Saturday. Default is set to 5, which is Friday",
        "link": null,
        "default": "5",
        "configurable": true,
        "contentKey": null
      },
      {
        "key": "WORK_HOUR_START",
        "required": false,
        "format": "integer",
        "description": "Hour of the day where business hours should start. 0-23. Default is set to 8, meaning business hours start at 8:00:00AM",
        "link": null,
        "default": "8",
        "configurable": true,
        "contentKey": null
      },
      {
        "key": "WORK_HOUR_END",
        "required": false,
        "format": "integer",
        "description": "Hour of the day where business hours should stop. 0-23. Default is set to 18, meaning business hours end at 18:59:59 or 6:59:59PM",
        "link": null,
        "default": "18",
        "configurable": true,
        "contentKey": null
      },
      {
        "key": "TWILIO_VOICE_WEBHOOK_URL",
        "required": true,
        "format": "text",
        "description": "The path to the webhook",
        "link": null,
        "default": "/voicemail",
        "configurable": false,
        "contentKey": null
      }
    ],
    "forward-message-sparkpost": [
      {
        "key": "SPARKPOST_API_KEY",
        "required": true,
        "format": "secret",
        "description": "Your SparkPost API key",
        "link": "https://www.sparkpost.com/docs/getting-started/create-api-keys/",
        "default": null,
        "configurable": true,
        "contentKey": null
      },
      {
        "key": "TO_EMAIL_ADDRESS",
        "required": true,
        "format": "email",
        "description": "Messages sent to your Twilio number will be forwarded to this email address",
        "link": null,
        "default": null,
        "configurable": true,
        "contentKey": null
      },
      {
        "key": "FROM_EMAIL_ADDRESS",
        "required": true,
        "format": "email",
        "description": "The email address that SparkPost should send the email from",
        "link": null,
        "default": null,
        "configurable": true,
        "contentKey": null
      },
      {
        "key": "TWILIO_SMS_WEBHOOK_URL",
        "required": true,
        "format": "text",
        "description": "The path to the webhook",
        "link": null,
        "default": "/forward-message-sparkpost",
        "configurable": false,
        "contentKey": null
      }
    ],
    "airtable": [
      {
        "key": "AIRTABLE_API_KEY",
        "required": true,
        "format": "secret",
        "description": "Your Airtable API Key",
        "link": "https://support.airtable.com/hc/en-us/articles/219046777-How-do-I-get-my-API-key-",
        "default": null,
        "configurable": true,
        "contentKey": null
      },
      {
        "key": "AIRTABLE_BASE_ID",
        "required": true,
        "format": "text",
        "description": "Your Airtable Base ID",
        "link": "https://airtable.com/api",
        "default": "appAbcD12efG3HijK",
        "configurable": true,
        "contentKey": null
      },
      {
        "key": "AIRTABLE_TABLE_NAME",
        "required": true,
        "format": "text",
        "description": "Your Airtable Table Name",
        "link": null,
        "default": "Table 1",
        "configurable": true,
        "contentKey": null
      },
      {
        "key": "TWILIO_PHONE_NUMBER",
        "required": true,
        "format": "phone_number",
        "description": "The Twilio phone number to send broadcast SMS from",
        "link": null,
        "default": "+12223334444",
        "configurable": true,
        "contentKey": null
      },
      {
        "key": "TWILIO_SMS_WEBHOOK_URL",
        "required": true,
        "format": "text",
        "description": "The path to the webhook",
        "link": null,
        "default": "/save-sms",
        "configurable": false,
        "contentKey": null
      }
    ],
    "conference": [
      {
        "key": "TWILIO_VOICE_WEBHOOK_URL",
        "required": true,
        "format": "text",
        "description": "The path to the webhook",
        "link": null,
        "default": "/conference",
        "configurable": false,
        "contentKey": null
      }
    ],
    "stripe-payment-link-sms": [
      {
        "key": "STRIPE_SECRET_KEY",
        "required": true,
        "format": "secret",
        "description": "A Stripe secret key",
        "link": "https://dashboard.stripe.com/test/apikeys",
        "default": null,
        "configurable": true,
        "contentKey": null
      },
      {
        "key": "TWILIO_PHONE_NUMBER",
        "required": false,
        "format": "phone_number",
        "description": "Sender phone number. Default is \"STRIPEDEMO\"",
        "link": "https://www.twilio.com/console/phone-numbers/getting-started",
        "default": null,
        "configurable": true,
        "contentKey": null
      },
      {
        "key": "TWILIO_SMS_WEBHOOK_URL",
        "required": true,
        "format": "text",
        "description": "The path to the webhook",
        "link": null,
        "default": "/create-invoice",
        "configurable": false,
        "contentKey": null
      }
    ],
    "stripe-sms-receipt": [
      {
        "key": "STRIPE_SECRET_KEY",
        "required": true,
        "format": "secret",
        "description": "A Stripe secret key",
        "link": "https://dashboard.stripe.com/test/apikeys",
        "default": null,
        "configurable": true,
        "contentKey": null
      },
      {
        "key": "TWILIO_PHONE_NUMBER",
        "required": false,
        "format": "phone_number",
        "description": "Sender phone number. Default is \"STRIPEDEMO\"",
        "link": "https://www.twilio.com/console/phone-numbers/getting-started",
        "default": null,
        "configurable": true,
        "contentKey": null
      }
    ],
    "chat-token": [
      {
        "key": "API_KEY",
        "required": true,
        "format": "text",
        "description": "API key for your Twilio Account",
        "link": "https://www.twilio.com/console/runtime/api-keys/create",
        "default": null,
        "configurable": true,
        "contentKey": null
      },
      {
        "key": "API_SECRET",
        "required": true,
        "format": "secret",
        "description": "API secret for your API Key",
        "link": "https://www.twilio.com/console/runtime/api-keys/create",
        "default": null,
        "configurable": true,
        "contentKey": null
      },
      {
        "key": "CHAT_SERVICE_SID",
        "required": true,
        "format": "sid",
        "description": "SID of your Twilio Chat Service",
        "link": "https://www.twilio.com/docs/api/chat/rest/services",
        "default": null,
        "configurable": true,
        "contentKey": null
      }
    ],
    "sync-token": [
      {
        "key": "API_KEY",
        "required": true,
        "format": "text",
        "description": "API key for your Twilio Account",
        "link": "https://www.twilio.com/console/runtime/api-keys/create",
        "default": null,
        "configurable": true,
        "contentKey": null
      },
      {
        "key": "API_SECRET",
        "required": true,
        "format": "secret",
        "description": "API secret for your API Key",
        "link": "https://www.twilio.com/console/runtime/api-keys/create",
        "default": null,
        "configurable": true,
        "contentKey": null
      },
      {
        "key": "SYNC_SERVICE_SID",
        "required": true,
        "format": "sid",
        "description": "SID of your Twilio Sync Service",
        "link": "https://www.twilio.com/docs/api/sync/rest/services",
        "default": null,
        "configurable": true,
        "contentKey": null
      }
    ],
    "video-token": [
      {
        "key": "API_KEY",
        "required": true,
        "format": "text",
        "description": "API key for your Twilio Account",
        "link": "https://www.twilio.com/console/runtime/api-keys/create",
        "default": null,
        "configurable": true,
        "contentKey": null
      },
      {
        "key": "API_SECRET",
        "required": true,
        "format": "secret",
        "description": "API secret for your API Key",
        "link": "https://www.twilio.com/console/runtime/api-keys/create",
        "default": null,
        "configurable": true,
        "contentKey": null
      }
    ],
    "hunt": [
      {
        "key": "PHONE_NUMBERS",
        "required": true,
        "format": "phone_number",
        "description": "A comma separated list of numbers in E.164 format that you want to dial in order",
        "link": null,
        "default": "+12223334444,+491761234567",
        "configurable": true,
        "contentKey": null
      },
      {
        "key": "FINAL_URL",
        "required": false,
        "format": "url",
        "description": "A URL to redirect the call to if none of the numbers answer. If this is not supplied then the call will just hang up once it has exhausted all the options",
        "link": null,
        "default": null,
        "configurable": true,
        "contentKey": null
      },
      {
        "key": "TWILIO_VOICE_WEBHOOK_URL",
        "required": true,
        "format": "text",
        "description": "The path to the webhook",
        "link": null,
        "default": "/hunt",
        "configurable": false,
        "contentKey": null
      }
    ],
    "http-redirect": [
      {
        "key": "HTTP_REDIRECT_URL",
        "required": true,
        "format": "url",
        "description": "The URL you want your redirect Function to redirect to",
        "link": null,
        "default": null,
        "configurable": true,
        "contentKey": null
      }
    ],
    "temp-storage": [],
    "verify": [
      {
        "key": "VERIFY_SERVICE_SID",
        "required": true,
        "format": "sid",
        "description": "SID of your Twilio Verify Service",
        "link": "https://www.twilio.com/console/verify/services",
        "default": null,
        "configurable": true,
        "contentKey": null
      }
    ],
    "blocklist-call": [
      {
        "key": "BLOCKLIST",
        "required": true,
        "format": "list(phone_number)",
        "description": "Only phone numbers in this comma-separated list will be allowed to join the conference. All phone numbers must follow the E.164 format",
        "link": "https://www.twilio.com/docs/glossary/what-e164",
        "default": "+12125551234,+17025556789",
        "configurable": true,
        "contentKey": null
      },
      {
        "key": "TWILIO_VOICE_WEBHOOK_URL",
        "required": true,
        "format": "text",
        "description": "The path to the webhook",
        "link": null,
        "default": "/blocklist-call",
        "configurable": false,
        "contentKey": null
      }
    ],
    "funlet-echo": [
      {
        "key": "FUNLET_ECHO_TWIML",
        "required": true,
        "format": "text",
        "description": "The default TwiML to echo back (can be overridden by the Twiml URL parameter)",
        "link": "https://www.twilio.com/docs/voice/twiml",
        "default": "<Response><Say>Hello, world!</Say></Response>",
        "configurable": true,
        "contentKey": null
      },
      {
        "key": "TWILIO_VOICE_WEBHOOK_URL",
        "required": true,
        "format": "text",
        "description": "The path to the webhook",
        "link": null,
        "default": "/funlet-echo",
        "configurable": false,
        "contentKey": null
      }
    ],
    "funlet-simple-message": [
      {
        "key": "FUNLET_MESSAGE_1",
        "required": true,
        "format": "text",
        "description": "The first URL to <Play>, or string to <Say>.",
        "link": null,
        "default": "Hello, world!",
        "configurable": true,
        "contentKey": null
      },
      {
        "key": "FUNLET_MESSAGE_2",
        "required": true,
        "format": "text",
        "description": "The second URL to <Play>, or string to <Say>.",
        "link": null,
        "default": null,
        "configurable": true,
        "contentKey": null
      },
      {
        "key": "FUNLET_MESSAGE_3",
        "required": true,
        "format": "text",
        "description": "The third URL to <Play>, or string to <Say>.",
        "link": null,
        "default": null,
        "configurable": true,
        "contentKey": null
      },
      {
        "key": "FUNLET_MESSAGE_4",
        "required": true,
        "format": "text",
        "description": "The fourth URL to <Play>, or string to <Say>.",
        "link": null,
        "default": null,
        "configurable": true,
        "contentKey": null
      },
      {
        "key": "FUNLET_MESSAGE_5",
        "required": true,
        "format": "text",
        "description": "The fifth URL to <Play>, or string to <Say>.",
        "link": null,
        "default": null,
        "configurable": true,
        "contentKey": null
      },
      {
        "key": "TWILIO_VOICE_WEBHOOK_URL",
        "required": true,
        "format": "text",
        "description": "The path to the webhook",
        "link": null,
        "default": "/funlet-simple-message",
        "configurable": false,
        "contentKey": null
      }
    ],
    "funlet-simple-menu": [
      {
        "key": "FUNLET_MENU_MESSAGE",
        "required": true,
        "format": "text",
        "description": "The URL of a media file to <Play>, or a string to <Say>, to greet the caller. Can be overridden by the Message URL parameter.",
        "link": null,
        "default": "Hello! Please select an option.",
        "configurable": true,
        "contentKey": null
      },
      {
        "key": "TWILIO_VOICE_WEBHOOK_URL",
        "required": true,
        "format": "text",
        "description": "The path to the webhook",
        "link": null,
        "default": "/funlet-simple-menu",
        "configurable": false,
        "contentKey": null
      }
    ],
    "funlet-whisper": [
      {
        "key": "FUNLET_WHISPER_HUMAN_CHECK",
        "required": true,
        "format": "text",
        "description": "If \"true\", check that the recipient is human by having them press a button.",
        "link": null,
        "default": "false",
        "configurable": true,
        "contentKey": null
      },
      {
        "key": "TWILIO_VOICE_WEBHOOK_URL",
        "required": true,
        "format": "text",
        "description": "The path to the webhook",
        "link": null,
        "default": "/funlet-whisper",
        "configurable": false,
        "contentKey": null
      }
    ],
    "funlet-forward": [
      {
        "key": "FUNLET_FORWARD_PHONE_NUMBER",
        "required": true,
        "format": "phone_number",
        "description": "Calls made to your Twilio number will get forwarded to this E.164-formatted phone number",
        "link": "https://www.twilio.com/docs/glossary/what-e164",
        "default": "+12223334444",
        "configurable": true,
        "contentKey": null
      },
      {
        "key": "TWILIO_VOICE_WEBHOOK_URL",
        "required": true,
        "format": "text",
        "description": "The path to the webhook",
        "link": null,
        "default": "/funlet-forward",
        "configurable": false,
        "contentKey": null
      }
    ],
    "funlet-call-me": [
      {
        "key": "FUNLET_CALLME_PHONE_NUMBER",
        "required": true,
        "format": "phone_number",
        "description": "Calls made to your Twilio number will get forwarded to this E.164-formatted phone number",
        "link": "https://www.twilio.com/docs/glossary/what-e164",
        "default": "+12223334444",
        "configurable": true,
        "contentKey": null
      },
      {
        "key": "TWILIO_VOICE_WEBHOOK_URL",
        "required": true,
        "format": "text",
        "description": "The path to the webhook",
        "link": null,
        "default": "/funlet-call-me",
        "configurable": false,
        "contentKey": null
      }
    ],
    "funlet-simulring": [
      {
        "key": "FUNLET_SIMULRING_PHONE_NUMBERS",
        "required": true,
        "format": "list(phone_number)",
        "description": "The phone numbers in this comma-separated list will be called simultaneously. All phone numbers must follow the E.164 format",
        "link": "https://www.twilio.com/docs/glossary/what-e164",
        "default": "+12345551234,+12345556789",
        "configurable": true,
        "contentKey": null
      },
      {
        "key": "TWILIO_VOICE_WEBHOOK_URL",
        "required": true,
        "format": "text",
        "description": "The path to the webhook",
        "link": null,
        "default": "/funlet-simulring",
        "configurable": false,
        "contentKey": null
      }
    ],
    "funlet-find-me": [
      {
        "key": "FUNLET_FINDME_PHONE_NUMBERS",
        "required": true,
        "format": "list(phone_number)",
        "description": "The phone numbers in this comma-separated list will be called in order. All phone numbers must follow the E.164 format",
        "link": "https://www.twilio.com/docs/glossary/what-e164",
        "default": "+12345551234,+12345556789",
        "configurable": true,
        "contentKey": null
      },
      {
        "key": "TWILIO_VOICE_WEBHOOK_URL",
        "required": true,
        "format": "text",
        "description": "The path to the webhook",
        "link": null,
        "default": "/funlet-find-me",
        "configurable": false,
        "contentKey": null
      }
    ],
    "voice-client-javascript": [
      {
        "key": "APP_NAME",
        "required": true,
        "format": "text",
        "description": "Choose a name for your application",
        "link": null,
        "default": "voice-client-javascript",
        "configurable": true,
        "contentKey": null
      },
      {
        "key": "ADMIN_PASSWORD",
        "required": true,
        "format": "text",
        "description": "Set a password for your app. Users who want to use the admin interface will have to use this password to access it",
        "link": null,
        "default": "default",
        "configurable": true,
        "contentKey": null
      }
    ],
    "voice-javascript-sdk": [
      {
        "key": "APP_NAME",
        "required": true,
        "format": "text",
        "description": "Choose a name for your application",
        "link": null,
        "default": "voice-javascript-sdk",
        "configurable": true,
        "contentKey": null
      },
      {
        "key": "ADMIN_PASSWORD",
        "required": true,
        "format": "text",
        "description": "Set a password for your app. Users who want to use the admin interface will have to use this password to access it",
        "link": null,
        "default": "default",
        "configurable": true,
        "contentKey": null
      }
    ],
    "conversations": [
      {
        "key": "STUDIO_FLOW_SID",
        "required": true,
        "format": "sid",
        "description": "The SID of the Studio Flow you want to use Conversations with. This number is found on your Studio Dashboard",
        "link": "https://www.twilio.com/console/studio/dashboard",
        "default": "FWxxxxxxxxx",
        "configurable": true,
        "contentKey": null
      }
    ],
    "sip-quickstart": [
      {
        "key": "APP_NAME",
        "required": true,
        "format": "text",
        "description": "Choose a name for your application",
        "link": null,
        "default": "SIP Quickstart",
        "configurable": true,
        "contentKey": null
      },
      {
        "key": "ADMIN_PASSWORD",
        "required": true,
        "format": "text",
        "description": "Set a password for your app. Users who want to use the admin interface will have to use this password to access it",
        "link": null,
        "default": "default",
        "configurable": true,
        "contentKey": null
      },
      {
        "key": "DEFAULT_SIP_USER_PASSWORD",
        "required": true,
        "format": "text",
        "description": "The default password for your SIP user",
        "link": null,
        "default": "ThisIs1Password!",
        "configurable": true,
        "contentKey": null
      }
    ],
    "conference-verify": [
      {
        "key": "VERIFY_SERVICE_SID",
        "required": true,
        "format": "sid",
        "description": "SID of your Twilio Verify Service",
        "link": "https://www.twilio.com/console/verify/services",
        "default": null,
        "configurable": true,
        "contentKey": null
      },
      {
        "key": "MODERATOR_PHONE_NUMBER",
        "required": true,
        "format": "phone_number",
        "description": "Phone number of the moderator. Conference starts when this number joins. In E.164 format",
        "link": null,
        "default": null,
        "configurable": true,
        "contentKey": null
      },
      {
        "key": "VALID_PARTICIPANTS",
        "required": true,
        "format": "list(phone_number)",
        "description": "Only phone numbers in this comma-separated list will be allowed to join the conference. All phone number must use E.164 format",
        "link": null,
        "default": null,
        "configurable": true,
        "contentKey": null
      },
      {
        "key": "TWILIO_VOICE_WEBHOOK_URL",
        "required": true,
        "format": "text",
        "description": "The path to the webhook",
        "link": null,
        "default": "/verify-conference",
        "configurable": false,
        "contentKey": null
      }
    ],
    "conference-pin": [
      {
        "key": "CONFERENCE_PIN",
        "required": true,
        "format": "integer",
        "description": "Choose a PIN code (only digits) for your app. Callers have to enter this code to be connected to your conference line",
        "link": null,
        "default": null,
        "configurable": true,
        "contentKey": null
      },
      {
        "key": "TWILIO_VOICE_WEBHOOK_URL",
        "required": true,
        "format": "text",
        "description": "The path to the webhook",
        "link": null,
        "default": "/conference-with-pin",
        "configurable": false,
        "contentKey": null
      }
    ],
    "conference-caller-gated": [
      {
        "key": "MODERATOR_PHONE_NUMBER",
        "required": true,
        "format": "phone_number",
        "description": "Phone number of the moderator. Conference starts when this number joins. In E.164 format",
        "link": null,
        "default": null,
        "configurable": true,
        "contentKey": null
      },
      {
        "key": "VALID_PARTICIPANTS",
        "required": true,
        "format": "list(phone_number)",
        "description": "Only phone numbers in this comma-separated list will be allowed to join the conference. All phone numbers must follow the E.164 format",
        "link": "https://www.twilio.com/docs/glossary/what-e164",
        "default": null,
        "configurable": true,
        "contentKey": null
      },
      {
        "key": "TWILIO_VOICE_WEBHOOK_URL",
        "required": true,
        "format": "text",
        "description": "The path to the webhook",
        "link": null,
        "default": "/gated-conference",
        "configurable": false,
        "contentKey": null
      }
    ],
    "video": [
      {
        "key": "API_KEY",
        "required": true,
        "format": "text",
        "description": "API key for your Twilio Account",
        "link": "https://www.twilio.com/console/project/api-keys",
        "default": null,
        "configurable": true,
        "contentKey": null
      },
      {
        "key": "API_SECRET",
        "required": true,
        "format": "secret",
        "description": "API secret for your API Key",
        "link": "https://www.twilio.com/console/project/api-keys",
        "default": null,
        "configurable": true,
        "contentKey": null
      },
      {
        "key": "ROOM_NAME",
        "required": true,
        "format": "text",
        "description": "Choose a room name for your video call",
        "link": null,
        "default": null,
        "configurable": true,
        "contentKey": null
      },
      {
        "key": "PASSCODE",
        "required": true,
        "format": "text",
        "description": "Choose a passcode for your app. Users have to use this passcode to enter the video call",
        "link": null,
        "default": null,
        "configurable": true,
        "contentKey": null
      }
    ],
    "sms-notifications": [
      {
        "key": "TWILIO_PHONE_NUMBER",
        "required": true,
        "format": "phone_number",
        "description": "The Twilio phone number to send broadcast SMS from",
        "link": null,
        "default": null,
        "configurable": true,
        "contentKey": null
      },
      {
        "key": "PASSCODE",
        "required": true,
        "format": "text",
        "description": "Choose a passcode for your app. Users have to use this passcode to send SMS broadcasts",
        "link": null,
        "default": null,
        "configurable": true,
        "contentKey": null
      }
    ],
    "voice-ivr": [
      {
        "key": "MY_PHONE_NUMBER",
        "required": true,
        "format": "phone_number",
        "description": "Your phone number",
        "link": null,
        "default": "+12223334444",
        "configurable": true,
        "contentKey": null
      },
      {
        "key": "TWILIO_VOICE_WEBHOOK_URL",
        "required": true,
        "format": "text",
        "description": "The path to the webhook",
        "link": null,
        "default": "/voice-ivr",
        "configurable": false,
        "contentKey": null
      }
    ],
    "magic-links": [
      {
        "key": "VERIFY_SERVICE_SID",
        "required": true,
        "format": "sid",
        "description": "SID of your Twilio Verify Service",
        "link": "https://www.twilio.com/console/verify/services",
        "default": null,
        "configurable": true,
        "contentKey": null
      },
      {
        "key": "CALLBACK_PATH",
        "required": true,
        "format": "text",
        "description": "URL path linked in the email template to check verifications",
        "link": null,
        "default": "verify.html",
        "configurable": true,
        "contentKey": null
      }
    ],
    "verify-dashboard": [
      {
        "key": "VERIFY_SERVICE_SID",
        "required": true,
        "format": "sid",
        "description": "SID of your Twilio Verify Service",
        "link": "https://www.twilio.com/console/verify/services",
        "default": null,
        "configurable": true,
        "contentKey": null
      }
    ],
    "verify-totp": [
      {
        "key": "VERIFY_SERVICE_SID",
        "required": true,
        "format": "sid",
        "description": "SID of your Twilio Verify Service",
        "link": "https://www.twilio.com/console/verify/services",
        "default": null,
        "configurable": true,
        "contentKey": null
      }
    ],
    "verify-totp-sms": [
      {
        "key": "VERIFY_SERVICE_SID",
        "required": true,
        "format": "sid",
        "description": "SID of your Twilio Verify Service",
        "link": "https://www.twilio.com/console/verify/services",
        "default": null,
        "configurable": true,
        "contentKey": null
      }
    ],
    "verify-retry": [
      {
        "key": "VERIFY_SERVICE_SID",
        "required": true,
        "format": "sid",
        "description": "SID of your Twilio Verify Service",
        "link": "https://www.twilio.com/console/verify/services",
        "default": null,
        "configurable": true,
        "contentKey": null
      }
    ],
    "verify-push-authy-backend": [
      {
        "key": "VERIFY_SERVICE_SID",
        "required": true,
        "format": "sid",
        "description": "SID of your Twilio Verify Service",
        "link": "https://www.twilio.com/console/verify/services",
        "default": null,
        "configurable": true,
        "contentKey": null
      },
      {
        "key": "IDENTITY_PROCESSING",
        "required": false,
        "format": "text",
        "description": "Define if the identity field will be hashed or will be taken as it is, possible values hash or raw",
        "link": null,
        "default": "hash",
        "configurable": true,
        "contentKey": null
      }
    ],
    "verify-push-backend": [
      {
        "key": "VERIFY_SERVICE_SID",
        "required": true,
        "format": "sid",
        "description": "SID of your Twilio Verify Service",
        "link": "https://www.twilio.com/console/verify/services",
        "default": null,
        "configurable": true,
        "contentKey": null
      },
      {
        "key": "IDENTITY_PROCESSING",
        "required": false,
        "format": "text",
        "description": "Define if the identity field will be hashed or will be taken as it is, possible values hash or raw",
        "link": null,
        "default": "hash",
        "configurable": true,
        "contentKey": null
      }
    ],
    "verified-broadcast": [
      {
        "key": "TWILIO_PHONE_NUMBER",
        "required": true,
        "format": "phone_number",
        "description": "The Twilio phone number to send broadcast SMS from",
        "link": null,
        "default": null,
        "configurable": true,
        "contentKey": null
      },
      {
        "key": "PASSCODE",
        "required": true,
        "format": "secret",
        "description": "Choose a passcode for your app. Users have to use this passcode to send SMS broadcasts or delete all subscriptions",
        "link": null,
        "default": null,
        "configurable": true,
        "contentKey": null
      },
      {
        "key": "MESSAGING_SERVICE_SID",
        "required": false,
        "format": "sid",
        "description": "SID of a Twilio Messaging Service. Otherwise one will automatically be provisioned for you.",
        "link": "https://console.twilio.com/us1/develop/sms/services",
        "default": null,
        "configurable": true,
        "contentKey": null
      },
      {
        "key": "BROADCAST_NOTIFY_SERVICE_SID",
        "required": false,
        "format": "sid",
        "description": "SID of your Twilio Notify Service. Otherwise one will automatically be provisioned for you.",
        "link": "https://www.twilio.com/console/notify/services",
        "default": null,
        "configurable": true,
        "contentKey": null
      },
      {
        "key": "VERIFY_SERVICE_SID",
        "required": false,
        "format": "sid",
        "description": "SID of your Twilio Verify Service. Otherwise one will automatically be provisioned for you.",
        "link": "https://www.twilio.com/console/verify/services",
        "default": null,
        "configurable": true,
        "contentKey": null
      }
    ],
    "international-telephone-input": [],
    "forward-message-mailgun": [
      {
        "key": "MAILGUN_API_KEY",
        "required": true,
        "format": "secret",
        "description": "Your Mailgun API key",
        "link": "https://app.mailgun.com/app/account/security/api_keys",
        "default": null,
        "configurable": true,
        "contentKey": null
      },
      {
        "key": "MG_VERIFIED_DOMAIN",
        "required": true,
        "format": "text",
        "description": "Your Mailgun verified domain you want to send emails from",
        "link": null,
        "default": null,
        "configurable": true,
        "contentKey": null
      },
      {
        "key": "TO_EMAIL_ADDRESS",
        "required": true,
        "format": "email",
        "description": "Messages sent to your Twilio number will be forwarded to this email address",
        "link": null,
        "default": null,
        "configurable": true,
        "contentKey": null
      },
      {
        "key": "FROM_EMAIL_ADDRESS",
        "required": true,
        "format": "email",
        "description": "The email address that Mailgun should send the email from",
        "link": null,
        "default": null,
        "configurable": true,
        "contentKey": null
      },
      {
        "key": "TWILIO_SMS_WEBHOOK_URL",
        "required": true,
        "format": "text",
        "description": "The path to the webhook",
        "link": null,
        "default": "/forward-message-mailgun",
        "configurable": false,
        "contentKey": null
      }
    ],
    "json-webhook": [
      {
        "key": "WEBHOOK_URL",
        "required": true,
        "format": "text",
        "description": "The URL for the webhook this function should call",
        "link": null,
        "default": null,
        "configurable": true,
        "contentKey": null
      },
      {
        "key": "TWILIO_SMS_WEBHOOK_URL",
        "required": true,
        "format": "text",
        "description": "The path to the Twilio Function webhook",
        "link": null,
        "default": "/event-to-webhook",
        "configurable": false,
        "contentKey": null
      }
    ],
    "sms-broadcast": [
      {
        "key": "BROADCAST_NOTIFY_SERVICE_SID",
        "required": true,
        "format": "sid",
        "description": "SID of your Twilio Notify Service (starts with IS)",
        "link": "https://www.twilio.com/console/notify/services",
        "default": null,
        "configurable": true,
        "contentKey": null
      },
      {
        "key": "BROADCAST_ADMIN_NUMBERS",
        "required": true,
        "format": "phone_number",
        "description": "A comma separated list of numbers in E.164 format that are allowed to trigger a broadcast",
        "link": null,
        "default": "+12223334444,+491761234567",
        "configurable": true,
        "contentKey": null
      },
      {
        "key": "TWILIO_SMS_WEBHOOK_URL",
        "required": true,
        "format": "text",
        "description": "The path to the webhook",
        "link": null,
        "default": "/broadcast",
        "configurable": false,
        "contentKey": null
      }
    ],
    "masked-number": [
      {
        "key": "MY_PHONE_NUMBER",
        "required": true,
        "format": "phone_number",
        "description": "Messages sent to your Twilio number will get forwarded to this E.164-formatted phone number",
        "link": "https://www.twilio.com/docs/glossary/what-e164",
        "default": "+12223334444",
        "configurable": true,
        "contentKey": null
      },
      {
        "key": "TWILIO_SMS_WEBHOOK_URL",
        "required": true,
        "format": "text",
        "description": "The path to the webhook",
        "link": null,
        "default": "/relay-sms",
        "configurable": false,
        "contentKey": null
      }
    ],
    "vaccine-standby": [
      {
        "key": "TWILIO_PHONE_NUMBER",
        "required": true,
        "format": "phone_number",
        "description": "Your Twilio phone number for sending and receiving messages",
        "link": null,
        "default": null,
        "configurable": true,
        "contentKey": null
      },
      {
        "key": "ADMIN_PASSWORD",
        "required": true,
        "format": "secret",
        "description": "Set a password for your app. Users who want to configure the app or view who messaged in, will need this password.",
        "link": null,
        "default": null,
        "configurable": true,
        "contentKey": null
      },
      {
        "key": "SALT",
        "required": true,
        "format": "secret",
        "description": "change the salt to invalidate existing auth tokens",
        "link": null,
        "default": "salty",
        "configurable": false,
        "contentKey": null
      },
      {
        "key": "FLOW_SID",
        "required": true,
        "format": "sid",
        "description": "SID of the Vaccine Intake Studio Flow",
        "link": null,
        "default": null,
        "configurable": false,
        "contentKey": null
      }
    ],
    "segment-event-notification": [
      {
        "key": "SEGMENT_EVENT",
        "required": true,
        "format": "text",
        "description": "The name of the Segment event you want to be notified about",
        "link": "https://segment.com/docs/connections/spec/track/#event",
        "default": null,
        "configurable": true,
        "contentKey": null
      },
      {
        "key": "TWILIO_PHONE_NUMBER",
        "required": true,
        "format": "phone_number",
        "description": "The Twilio phone number to send SMS notifications from",
        "link": null,
        "default": "+12223334444",
        "configurable": true,
        "contentKey": null
      },
      {
        "key": "MY_PHONE_NUMBER",
        "required": true,
        "format": "phone_number",
        "description": "Segment event notifications will be sent to this E.164-formatted phone number",
        "link": "https://www.twilio.com/docs/glossary/what-e164",
        "default": "+12223334444",
        "configurable": true,
        "contentKey": null
      }
    ],
    "google-sheets": [
      {
        "key": "GOOGLE_CREDENTIALS",
        "required": true,
        "format": "file(json)",
        "description": "A JSON key file for your Google Sheets service account",
        "link": "https://cloud.google.com/iam/docs/creating-managing-service-account-keys#creating_service_account_keys",
        "default": "/auth.json",
        "configurable": true,
        "contentKey": "GOOGLE_CREDENTIALS_CONTENT"
      },
      {
        "key": "DOCUMENT_ID",
        "required": true,
        "format": "text",
        "description": "The document ID for your Google Sheets spreadsheet (from its URL: https://docs.google.com/spreadsheets/d/[id]/edit)",
        "link": null,
        "default": null,
        "configurable": true,
        "contentKey": null
      },
      {
        "key": "SHEET_NAME",
        "required": true,
        "format": "text",
        "description": "The spreadsheet name to log to within your Google Sheets document",
        "link": null,
        "default": "Sheet1",
        "configurable": true,
        "contentKey": null
      },
      {
        "key": "TWILIO_SMS_WEBHOOK_URL",
        "required": true,
        "format": "text",
        "description": "The path to the webhook",
        "link": null,
        "default": "/log-sms",
        "configurable": false,
        "contentKey": null
      }
    ],
    "covid-vaccine-faq-bot": [
      {
        "key": "TWILIO_PHONE_NUMBER",
        "required": true,
        "format": "phone_number",
        "description": "Your Twilio phone number for sending and receiving messages",
        "link": null,
        "default": null,
        "configurable": true,
        "contentKey": null
      },
      {
        "key": "GOOGLE_CLOUD_PROJECT_ID",
        "required": true,
        "format": "text",
        "description": "Your Google Cloud Project ID",
        "link": "https://cloud.google.com/dialogflow/cx/docs/quick/setup#project",
        "default": null,
        "configurable": true,
        "contentKey": null
      },
      {
        "key": "GOOGLE_APPLICATION_CREDENTIALS",
        "required": true,
        "format": "file(json)",
        "description": "A JSON key file for your Google service account. If deploying via CodeExchange, paste the JSON contents of the service account key below.",
        "link": "https://cloud.google.com/iam/docs/creating-managing-service-account-keys#creating_service_account_keys",
        "default": "/service-account-key.json",
        "configurable": true,
        "contentKey": "SERVICE_ACCOUNT_KEY_CONTENT"
      },
      {
        "key": "LANGUAGE_CODE",
        "required": false,
        "format": "text",
        "description": "Language to be used by chatbot. Defaults to U.S. English (en-US). Do not change if using pre-build chatbot agents. If changing, set to Dialogflow language tag (e.g. es).",
        "link": "https://cloud.google.com/dialogflow/es/docs/reference/language",
        "default": "en-US",
        "configurable": true,
        "contentKey": null
      },
      {
        "key": "FLOW_SID",
        "required": true,
        "format": "sid",
        "description": "SID of the Vaccine Bot FAQ Studio Flow, will be set automatically by the app, no need to configure in advance",
        "link": null,
        "default": null,
        "configurable": false,
        "contentKey": null
      }
    ],
    "patient-appointment-management": [
      {
        "key": "APPLICATION_PASSWORD",
        "required": true,
        "format": "secret",
        "description": "Set a password for your app. Users who want download data in, will need this password.",
        "link": null,
        "default": null,
        "configurable": true,
        "contentKey": null
      },
      {
        "key": "SALT",
        "required": true,
        "format": "secret",
        "description": "change the salt to invalidate existing auth tokens",
        "link": null,
        "default": "salty",
        "configurable": false,
        "contentKey": null
      },
      {
        "key": "CUSTOMER_NAME",
        "required": true,
        "format": "text",
        "description": "Customer name to be displayed in SMS.",
        "link": null,
        "default": null,
        "configurable": true,
        "contentKey": null
      },
      {
        "key": "CUSTOMER_CODE",
        "required": true,
        "format": "text",
        "description": "Customer short name. Must be all lowercase one word without any spaces.",
        "link": null,
        "default": null,
        "configurable": true,
        "contentKey": null
      },
      {
        "key": "TWILIO_PHONE_NUMBER",
        "required": true,
        "format": "phone_number",
        "description": "Twilio phone number to send SMS from. Your patient will see this number.",
        "link": null,
        "default": null,
        "configurable": true,
        "contentKey": null
      },
      {
        "key": "REMINDER_OUTREACH_START",
        "required": true,
        "format": "text",
        "description": "Reminder outreach window start time local timezone (HHMM) inclusive. default 0000",
        "link": null,
        "default": "0000",
        "configurable": true,
        "contentKey": null
      },
      {
        "key": "REMINDER_OUTREACH_FINISH",
        "required": true,
        "format": "text",
        "description": "Reminder outreach window end time local timezone (HHMM) exclusive, default 2400",
        "link": null,
        "default": "2400",
        "configurable": true,
        "contentKey": null
      },
      {
        "key": "REMINDER_FIRST_TIMING",
        "required": true,
        "format": "text",
        "description": "Reminder 1st outreach offset (HHMM). default 4800",
        "link": null,
        "default": "4800",
        "configurable": true,
        "contentKey": null
      },
      {
        "key": "REMINDER_SECOND_TIMING",
        "required": true,
        "format": "text",
        "description": "Reminder 2nd outreach offset (HHMM). default 2400",
        "link": null,
        "default": "2400",
        "configurable": true,
        "contentKey": null
      },
      {
        "key": "DEPLOYER_AWS_ACCESS_KEY_ID",
        "required": true,
        "format": "text",
        "description": "AWS access key id to your AWS account with admin-level privilege",
        "link": null,
        "default": null,
        "configurable": true,
        "contentKey": null
      },
      {
        "key": "DEPLOYER_AWS_SECRET_ACCESS_KEY",
        "required": true,
        "format": "secret",
        "description": "AWS secret access key of your AWS access key id",
        "link": null,
        "default": null,
        "configurable": true,
        "contentKey": null
      },
      {
        "key": "AWS_REGION",
        "required": true,
        "format": "text",
        "description": "AWS region to deploy resources",
        "link": null,
        "default": "us-west-2",
        "configurable": false,
        "contentKey": null
      },
      {
        "key": "ADMINISTRATOR_PHONE",
        "required": true,
        "format": "phone_number",
        "description": "Administrator phone number to receive security code for 2nd factor authentication.",
        "link": null,
        "default": null,
        "configurable": true,
        "contentKey": null
      }
    ],
    "lookup": [],
    "contact-form": [
      {
        "key": "SENDGRID_API_KEY",
        "required": true,
        "format": "secret",
        "description": "Your SendGrid API key",
        "link": "https://sendgrid.com/docs/ui/account-and-settings/api-keys/",
        "default": null,
        "configurable": true,
        "contentKey": null
      },
      {
        "key": "TO_EMAIL_ADDRESS",
        "required": true,
        "format": "email",
        "description": "Messages submitted through the contact form will be sent to this email address",
        "link": null,
        "default": null,
        "configurable": true,
        "contentKey": null
      },
      {
        "key": "FROM_EMAIL_ADDRESS",
        "required": true,
        "format": "email",
        "description": "Messages submitted through the contact form will be sent from this email address",
        "link": null,
        "default": null,
        "configurable": true,
        "contentKey": null
      }
    ],
    "caller-id-forwarding": [
      {
        "key": "MY_PHONE_NUMBER",
        "required": true,
        "format": "phone_number",
        "description": "Calls made to your Twilio number will get forwarded to this e164-formatted phone number",
        "link": "https://www.twilio.com/docs/glossary/what-e164",
        "default": "+12223334444",
        "configurable": true,
        "contentKey": null
      },
      {
        "key": "TWILIO_VOICE_WEBHOOK_URL",
        "required": true,
        "format": "text",
        "description": "The path to the webhook",
        "link": null,
        "default": "/forward-call",
        "configurable": false,
        "contentKey": null
      }
    ],
    "frontline-quickstart": [
      {
        "key": "TWILIO_PHONE_NUMBER",
        "required": true,
        "format": "phone_number",
        "description": "Twilio phone number to send SMS from. Your patient will see this number.",
        "link": null,
        "default": null,
        "configurable": true,
        "contentKey": null
      },
      {
        "key": "EXAMPLE_CUSTOMER_1_PHONE_NUMBER",
        "required": true,
        "format": "phone_number",
        "description": "This is the phone number of your example customer. You can send and receive text messages to this number.",
        "link": null,
        "default": null,
        "configurable": true,
        "contentKey": null
      },
      {
        "key": "EXAMPLE_CUSTOMER_2_PHONE_NUMBER",
        "required": false,
        "format": "phone_number",
        "description": "(Optional) This is the phone number of your second example customer. You can send and receive text messages to this number.",
        "link": null,
        "default": null,
        "configurable": true,
        "contentKey": null
      },
      {
        "key": "SSO_USERNAME",
        "required": true,
        "format": "text",
        "description": "This is the username of the user that youve added to your Identity Provider (IdP) that you will use to login to Frontline.",
        "link": null,
        "default": null,
        "configurable": true,
        "contentKey": null
      }
    ],
    "video-token-backend": [
      {
        "key": "API_KEY_SID",
        "required": true,
        "format": "text",
        "description": "API key for your Twilio Account",
        "link": "https://www.twilio.com/console/runtime/api-keys/create",
        "default": null,
        "configurable": true,
        "contentKey": null
      },
      {
        "key": "API_KEY_SECRET",
        "required": true,
        "format": "secret",
        "description": "API secret for your API Key",
        "link": "https://www.twilio.com/console/runtime/api-keys/create",
        "default": null,
        "configurable": true,
        "contentKey": null
      }
    ],
    "verify-sna": [
      {
        "key": "ACCOUNT_SID",
        "required": true,
        "format": "sid",
        "description": "SID of your Twilio Account or Subaccount",
        "link": "https://www.twilio.com/console",
        "default": null,
        "configurable": true,
        "contentKey": null
      },
      {
        "key": "AUTH_TOKEN",
        "required": true,
        "format": "text",
        "description": "Auth Token of your Twilio Account or Subaacount",
        "link": "https://www.twilio.com/console",
        "default": null,
        "configurable": true,
        "contentKey": null
      },
      {
        "key": "VERIFY_SERVICE_SID",
        "required": true,
        "format": "sid",
        "description": "SID of your Twilio Verify Service",
        "link": "https://www.twilio.com/console/verify/services",
        "default": null,
        "configurable": true,
        "contentKey": null
      },
      {
        "key": "SYNC_SERVICE_SID",
        "required": true,
        "format": "sid",
        "description": "SID of your Twilio Sync Service",
        "link": "https://www.twilio.com/console/sync/services",
        "default": null,
        "configurable": true,
        "contentKey": null
      },
      {
        "key": "SYNC_MAP_SID",
        "required": true,
        "format": "sid",
        "description": "SID of the Sync Map in your Sync Service that you want to use for storage",
        "link": "https://www.twilio.com/console/sync/services",
        "default": null,
        "configurable": true,
        "contentKey": null
      }
    ],
    "experimental-flex-dialpad": [
      {
        "key": "TWILIO_WORKFLOW_SID",
        "required": true,
        "format": "text",
        "description": "SID of the TaskRouter workflow used for transfers",
        "link": null,
        "default": null,
        "configurable": false,
        "contentKey": null
      },
      {
        "key": "TWILIO_WORKSPACE_SID",
        "required": true,
        "format": "text",
        "description": "SID for the TaskRouter Workspace that contains your workflow",
        "link": null,
        "default": null,
        "configurable": false,
        "contentKey": null
      },
      {
        "key": "TWILIO_PHONE_NUMBER",
        "required": true,
        "format": "text",
        "description": "The phone number used for your transfers",
        "link": null,
        "default": null,
        "configurable": true,
        "contentKey": null
      }
    ],
    "list-numbers": [
      {
        "key": "Password",
        "required": true,
        "format": "text",
        "description": "Set the password that will allow you to use the application",
        "link": null,
        "default": "1",
        "configurable": true,
        "contentKey": null
      }
    ],
    "transfers": [
      {
        "key": "Password",
        "required": true,
        "format": "text",
        "description": "Set the password that will allow you to use the application",
        "link": null,
        "default": "1",
        "configurable": true,
        "contentKey": null
      }
    ],
    "verify-prefill": [
      {
        "key": "VERIFY_SERVICE_SID",
        "required": true,
        "format": "sid",
        "description": "SID of your Twilio Verify Service",
        "link": "https://www.twilio.com/console/verify/services",
        "default": null,
        "configurable": true,
        "contentKey": null
      }
    ],
    "reminder-message": [
      {
        "key": "MESSAGING_SERVICE_SID",
        "required": true,
        "format": "sid",
        "description": "SID of a Twilio Messaging Service that will be used for your reminder email.",
        "link": "https://console.twilio.com/us1/develop/sms/services",
        "default": null,
        "configurable": true,
        "contentKey": null
      },
      {
        "key": "DELAY_IN_MINUTES",
        "required": false,
        "format": "number",
        "description": "Delay of how many minutes it should take after the incoming message to sent out a reminder. Minimum: 15 minutes",
        "link": null,
        "default": null,
        "configurable": true,
        "contentKey": null
      },
      {
        "key": "TWILIO_SMS_WEBHOOK_URL",
        "required": true,
        "format": "text",
        "description": "The path to the webhook",
        "link": null,
        "default": "/respond",
        "configurable": false,
        "contentKey": null
      }
    ],
    "passkeys-backend": [
      {
        "key": "API_URL",
        "required": true,
        "format": "url",
        "description": "The URL of the comms API for passkeys",
        "link": null,
        "default": null,
        "configurable": true,
        "contentKey": null
      },
      {
        "key": "RELYING_PARTY",
        "required": true,
        "format": "url",
        "description": "The domain of the relying party",
        "link": null,
        "default": null,
        "configurable": true,
        "contentKey": null
      },
      {
        "key": "ANDROID_APP_KEYS",
        "required": false,
        "format": "list(text)",
        "description": "The domain of the adroid identity provider",
        "link": null,
        "default": null,
        "configurable": true,
        "contentKey": null
      }
    ],
    "ai-assistants-samples": [
      {
        "key": "ACCOUNT_SID",
        "required": true,
        "format": "sid",
        "description": "SID of your Twilio Account or Subaccount",
        "link": "https://www.twilio.com/console",
        "default": null,
        "configurable": true,
        "contentKey": null
      },
      {
        "key": "AUTH_TOKEN",
        "required": true,
        "format": "text",
        "description": "Auth Token of your Twilio Account or Subaacount",
        "link": "https://www.twilio.com/console",
        "default": null,
        "configurable": true,
        "contentKey": null
      },
      {
        "key": "ASSISTANT_SID",
        "required": true,
        "format": "text",
        "description": "The ID of your AI Assistant (starts with ai_asst_)",
        "link": null,
        "default": null,
        "configurable": false,
        "contentKey": null
      },
      {
        "key": "GOOGLE_MAPS_API_KEY",
        "required": true,
        "format": "text",
        "description": "API key for Google Maps service",
        "link": null,
        "default": null,
        "configurable": false,
        "contentKey": null
      },
      {
        "key": "OPENAI_API_KEY",
        "required": false,
        "format": "secret",
        "description": "API key for OpenAI used in Internet Search tool",
        "link": null,
        "default": null,
        "configurable": true,
        "contentKey": null
      },
      {
        "key": "EXA_API_KEY",
        "required": true,
        "format": "text",
        "description": "API key for Exa used in Internet Search tool",
        "link": null,
        "default": null,
        "configurable": false,
        "contentKey": null
      },
      {
        "key": "FLEX_WORKFLOW_SID",
        "required": true,
        "format": "text",
        "description": "Flex Workflow SID used for Flex Handoffs",
        "link": null,
        "default": null,
        "configurable": false,
        "contentKey": null
      },
      {
        "key": "FLEX_WORKSPACE_SID",
        "required": true,
        "format": "text",
        "description": "Flex Workspace SID used for Flex Handoffs",
        "link": null,
        "default": null,
        "configurable": false,
        "contentKey": null
      }
    ]
  }
}